COPYING.txt
MANIFEST.in
setup.py
testmyrest/testmyrest.py
testmyrest.egg-info/PKG-INFO
testmyrest.egg-info/SOURCES.txt
testmyrest.egg-info/dependency_links.txt
testmyrest.egg-info/top_level.txt