Metadata-Version: 1.1
Name: testmyrest
Version: 0.0.1
Summary: helper functions for RAML testing
Home-page: https://github.com/r-schmidtke/TestARest
Author: Robin Schmidtke
Author-email: robin@schmitke-ct.de
License: UNKNOWN
Platform: UNKNOWN
Classifier: Development Status :: 3 - Alpha
Classifier: Programming Language :: Python
Classifier: Environment :: Plugins
